memcord/__init__.py
memcord/archival.py
memcord/compression.py
memcord/importer.py
memcord/merger.py
memcord/models.py
memcord/query.py
memcord/search.py
memcord/server.py
memcord/storage.py
memcord/summarizer.py
memcord/temporal_parser.py
mseep_memcord-2.2.2.dist-info/METADATA
mseep_memcord-2.2.2.dist-info/WHEEL
mseep_memcord-2.2.2.dist-info/entry_points.txt
mseep_memcord-2.2.2.dist-info/licenses/LICENSE
mseep_memcord-2.2.2.dist-info/RECORD
