Metadata-Version: 2.4
Name: mseep-memcord
Version: 2.2.2
Summary: MCP server for chat memory management with summarization and file sharing
Author-email: mseep <support@skydeck.ai>
License: MIT
License-File: LICENSE
Requires-Python: >=3.10
Requires-Dist: aiofiles>=23.0
Requires-Dist: beautifulsoup4>=4.12.0
Requires-Dist: mcp>=0.3.0
Requires-Dist: nltk>=3.8
Requires-Dist: pandas>=2.0.0
Requires-Dist: pdfplumber>=0.10.0
Requires-Dist: pydantic>=2.0.0
Requires-Dist: python-magic>=0.4.27
Requires-Dist: requests>=2.31.0
Requires-Dist: trafilatura>=1.8.0
Provides-Extra: dev
Requires-Dist: black>=23.0.0; extra == 'dev'
Requires-Dist: factory-boy>=3.3.0; extra == 'dev'
Requires-Dist: psutil>=5.9.0; extra == 'dev'
Requires-Dist: pytest-asyncio>=0.21.0; extra == 'dev'
Requires-Dist: pytest-benchmark>=4.0.0; extra == 'dev'
Requires-Dist: pytest-cov>=4.0.0; extra == 'dev'
Requires-Dist: pytest-mock>=3.10.0; extra == 'dev'
Requires-Dist: pytest>=7.0.0; extra == 'dev'
Requires-Dist: ruff>=0.1.0; extra == 'dev'
Requires-Dist: selenium>=4.15.0; extra == 'dev'
Requires-Dist: webdriver-manager>=4.0.0; extra == 'dev'
